how/__init__.py
how/__main__.py
how/cli.py
how/crawler.py
how/util.py
askquestions-0.4.0.dist-info/LICENSE
askquestions-0.4.0.dist-info/METADATA
askquestions-0.4.0.dist-info/WHEEL
askquestions-0.4.0.dist-info/entry_points.txt
askquestions-0.4.0.dist-info/top_level.txt
askquestions-0.4.0.dist-info/RECORD
