Metadata-Version: 2.1
Name: askquestions
Version: 0.4.0
Summary: UNKNOWN
Home-page: https://github.com/ronnathaniel/how
Author: ronnathaniel
Author-email: rnathaniel7@gmail.com
License: UNKNOWN
Project-URL: Bug Tracker, https://github.com/ronnathaniel/how/issues
Keywords: python,python3,how,howto,howdoi,stackoverflow
Platform: UNKNOWN
Classifier: Intended Audience :: Developers
Classifier: Operating System :: OS Independent
Classifier: Programming Language :: Python
Classifier: Programming Language :: Python :: 2
Classifier: Programming Language :: Python :: 2.7
Classifier: Programming Language :: Python :: 3
Classifier: Programming Language :: Python :: 3.6
Classifier: Programming Language :: Python :: 3.7
Classifier: Programming Language :: Python :: 3.8
Classifier: Topic :: Software Development :: Libraries
Classifier: Topic :: Software Development :: Libraries :: Python Modules
Requires-Python: >=3.6
License-File: LICENSE
Requires-Dist: googlesearch-python
Requires-Dist: beautifulsoup4
Requires-Dist: requests
Requires-Dist: colorama
